odoo/addons/stock_product_pack/README.rst
odoo/addons/stock_product_pack/__init__.py
odoo/addons/stock_product_pack/__manifest__.py
odoo/addons/stock_product_pack/i18n/es.po
odoo/addons/stock_product_pack/i18n/fr.po
odoo/addons/stock_product_pack/i18n/it.po
odoo/addons/stock_product_pack/i18n/pt.po
odoo/addons/stock_product_pack/i18n/stock_product_pack.pot
odoo/addons/stock_product_pack/models/__init__.py
odoo/addons/stock_product_pack/models/product_product.py
odoo/addons/stock_product_pack/models/product_template.py
odoo/addons/stock_product_pack/models/stock_rule.py
odoo/addons/stock_product_pack/readme/CONTRIBUTORS.md
odoo/addons/stock_product_pack/readme/DESCRIPTION.md
odoo/addons/stock_product_pack/readme/USAGE.md
odoo/addons/stock_product_pack/security/ir.model.access.csv
odoo/addons/stock_product_pack/static/description/icon.png
odoo/addons/stock_product_pack/static/description/index.html
odoo/addons/stock_product_pack/tests/__init__.py
odoo/addons/stock_product_pack/tests/test_stock_product_pack.py
odoo/addons/stock_product_pack/views/product_template_views.xml
odoo_addon_stock_product_pack-18.0.1.0.0.2.dist-info/METADATA
odoo_addon_stock_product_pack-18.0.1.0.0.2.dist-info/WHEEL
odoo_addon_stock_product_pack-18.0.1.0.0.2.dist-info/top_level.txt
odoo_addon_stock_product_pack-18.0.1.0.0.2.dist-info/RECORD
