Metadata-Version: 2.1
Name: odoo-addon-stock_product_pack
Version: 18.0.1.0.0.2
Requires-Python: >=3.10
Requires-Dist: odoo-addon-product_pack==18.0.*
Requires-Dist: odoo==18.0.*
Summary: This module allows you to get the right available quantities of the packs
Home-page: https://github.com/OCA/product-pack
License: AGPL-3
Author: =?utf-8?q?NaN=C2=B7tic=2C_ADHOC_SA=2C_Tecnativa=2C_Odoo_Community_Association_=28OCA=29?=
Author-email: support@odoo-community.org
Classifier: Programming Language :: Python
Classifier: Framework :: Odoo
Classifier: Framework :: Odoo :: 18.0
Classifier: License :: OSI Approved :: GNU Affero General Public License v3
